{"_meta": {"schema_version": 2, "fetched_at_utc": "2025-12-15T07:50:51.762812+00:00", "ttl_hours": 24.0, "url": "https://www.screener.in/company/MAGNUM/", "http_status": 200, "source": "screener_requests"}, "data": {"symbol": "MAGNUM", "status": "ok", "note": null, "source": "screener_requests", "yoy_net_profit_growth_pct": -86.3169897377423, "curr_q_label": "Sep 2025", "prev_yoy_q_label": "Sep 2024", "curr_net_profit": 1.2, "prev_yoy_net_profit": 8.77, "net_row_key": "Net Profit +", "label_col": "Unnamed: 0", "yoy": -86.3169897377423, "title": "Magnum Ventures Ltd share price | About Magnum Ventures | Key Insights - Screener", "url": "https://www.screener.in/company/MAGNUM/", "http_status": 200}}