{"_meta": {"schema_version": 2, "fetched_at_utc": "2025-12-15T07:58:19.775409+00:00", "ttl_hours": 24.0, "url": "https://www.screener.in/company/PRAENG/consolidated/", "http_status": 200, "source": "screener_requests"}, "data": {"symbol": "PRAENG", "status": "ok", "note": null, "source": "screener_requests", "yoy_net_profit_growth_pct": 4.186795491143314, "curr_q_label": "Sep 2025", "prev_yoy_q_label": "Sep 2024", "curr_net_profit": -6.47, "prev_yoy_net_profit": -6.21, "net_row_key": "Net Profit +", "label_col": "Unnamed: 0", "yoy": 4.186795491143314, "title": "Prajay Engineers Syndicate Ltd share price | About Prajay Engineers | Key Insights - Screener", "url": "https://www.screener.in/company/PRAENG/consolidated/", "http_status": 200}}